lenspy/__init__.py
lenspy/__version__.py
lenspy-1.1.0.dist-info/LICENSE
lenspy-1.1.0.dist-info/METADATA
lenspy-1.1.0.dist-info/WHEEL
lenspy-1.1.0.dist-info/top_level.txt
lenspy-1.1.0.dist-info/RECORD
