Metadata-Version: 2.1
Name: lenspy
Version: 1.1.0
Summary: Plot big data with Python.
Home-page: UNKNOWN
Author: Seran Thirugnanam
License: MIT
Platform: UNKNOWN
Classifier: License :: OSI Approved :: MIT License
Classifier: Programming Language :: Python
Classifier: Programming Language :: Python :: 3
Classifier: Programming Language :: Python :: 3.6
Classifier: Programming Language :: Python :: Implementation :: CPython
Classifier: Programming Language :: Python :: Implementation :: PyPy
Requires-Python: >=3.6.0
Requires-Dist: pandas
Requires-Dist: plotly
Requires-Dist: dash
